client_app/__init__.py
client_app/client_app.py
client_app/client/__init__.py
client_app/client/add_contact.py
client_app/client/database.py
client_app/client/del_contact.py
client_app/client/main_window.py
client_app/client/main_window_conv.py
client_app/client/start_dialog.py
client_app/client/transport.py
client_app/common/__init__.py
client_app/common/constants.py
client_app/common/decos.py
client_app/common/descriptors.py
client_app/common/errors.py
client_app/common/metaclasses.py
client_app/common/utils.py
client_app/doc/__init__.py
client_app/loging/__init__.py
client_app/loging/client_conf_log.py
client_pyqt_chat_June_Araym51-0.0.1.dist-info/METADATA
client_pyqt_chat_June_Araym51-0.0.1.dist-info/WHEEL
client_pyqt_chat_June_Araym51-0.0.1.dist-info/top_level.txt
client_pyqt_chat_June_Araym51-0.0.1.dist-info/RECORD
