Metadata-Version: 2.1
Name: client-pyqt-chat-June-Araym51
Version: 0.0.1
Summary: messenger_client_project
Home-page: UNKNOWN
Author: Egor Ostroumov
Author-email: araimo@yandex.ru
License: UNKNOWN
Platform: UNKNOWN
Requires-Dist: pycryptodome
Requires-Dist: PyQt5
Requires-Dist: sqlalchemy
Requires-Dist: pycryptodomex
